darajapy/__init__.py
darajapy/access_token.py
darajapy/c2b.py
darajapy/keys.py
darajapy/lipanampesa.py
darajapy/password.py
darajapy/utils.py
daraja_py-1.0.1.dist-info/METADATA
daraja_py-1.0.1.dist-info/WHEEL
daraja_py-1.0.1.dist-info/top_level.txt
daraja_py-1.0.1.dist-info/RECORD
