Metadata-Version: 2.1
Name: daraja-py
Version: 1.0.1
Summary: Lipa na mpesa library
Home-page: https://github.com/kamauvick/daraja-py
Author: Victor Waichigo
Author-email: waichigovick@gmail.com
License: MIT
Download-URL: https://github.com/kamauvick/daraja-py.git
Platform: UNKNOWN
Classifier: License :: OSI Approved :: MIT License
Classifier: Programming Language :: Python :: 3
Classifier: Programming Language :: Python :: 3.7
Requires-Dist: requests
Requires-Dist: python-decouple
